superalgorithm/backtesting/__init__.py
superalgorithm/backtesting/analytics.py
superalgorithm/backtesting/upload.py
superalgorithm/data/data_provider.py
superalgorithm/data/data_source.py
superalgorithm/data/data_store.py
superalgorithm/data/ohlcv_aggregator.py
superalgorithm/data/providers/ccxt/__init__.py
superalgorithm/data/providers/ccxt/ccxt_data_source.py
superalgorithm/data/providers/ccxt/ccxt_helper.py
superalgorithm/data/providers/csv/__init__.py
superalgorithm/data/providers/csv/csv_data_source.py
superalgorithm/data/providers/csv/csv_helper.py
superalgorithm/exchange/__init__.py
superalgorithm/exchange/base_exchange.py
superalgorithm/exchange/ccxt_exchange.py
superalgorithm/exchange/paper_exchange.py
superalgorithm/exchange/status_tracker.py
superalgorithm/exchange/woo_exchange.py
superalgorithm/exchange/managers/order_manager.py
superalgorithm/exchange/managers/position_manager.py
superalgorithm/exchange/managers/trade_manager.py
superalgorithm/strategy/__init__.py
superalgorithm/strategy/base_strategy.py
superalgorithm/types/__init__.py
superalgorithm/types/data_types.py
superalgorithm/utils/api_client.py
superalgorithm/utils/async_task_manager.py
superalgorithm/utils/bar_utils.py
superalgorithm/utils/config.py
superalgorithm/utils/event_emitter.py
superalgorithm/utils/helpers.py
superalgorithm/utils/logging.py
superalgorithm/utils/unique_int_generator.py
superalgorithm-0.0.27.dist-info/LICENSE
superalgorithm-0.0.27.dist-info/METADATA
superalgorithm-0.0.27.dist-info/WHEEL
superalgorithm-0.0.27.dist-info/top_level.txt
superalgorithm-0.0.27.dist-info/RECORD
