Metadata-Version: 2.2
Name: superalgorithm
Version: 0.0.27
Summary: Python framework for algorithmic trading
Author-email: Super Algorithm <hello@superalgorithm.com>
License:                     GNU GENERAL PUBLIC LICENSE
Project-URL: Homepage, https://github.com/superalgorithm/superalgorithm
Keywords: project-superalgorithm,superalgorithm
Classifier: Development Status :: 5 - Production/Stable
Classifier: Intended Audience :: Developers
Classifier: Topic :: Software Development :: Build Tools
Classifier: License :: OSI Approved :: GNU General Public License (GPL)
Classifier: Programming Language :: Python :: 3.8
Classifier: Programming Language :: Python :: 3.9
Classifier: Programming Language :: Python :: 3.10
Classifier: Programming Language :: Python :: 3.11
Classifier: Programming Language :: Python :: 3.13
Requires-Python: >=3.8
License-File: LICENSE
Requires-Dist: pyyaml>=6.0.2
Requires-Dist: ccxt>=4.4.17
Requires-Dist: numpy>=2.0.1
Requires-Dist: requests>=2.32.3
Provides-Extra: dev
Requires-Dist: pytest>=8.3.4; extra == "dev"
Requires-Dist: pytest-asyncio>=0.23.8; extra == "dev"
Requires-Dist: tomli; extra == "dev"
Requires-Dist: tomli-w; extra == "dev"
